djavedt/__init__.py
djavedt-1.0.0.dist-info/LICENSE
djavedt-1.0.0.dist-info/METADATA
djavedt-1.0.0.dist-info/WHEEL
djavedt-1.0.0.dist-info/top_level.txt
djavedt-1.0.0.dist-info/RECORD
