Metadata-Version: 2.1
Name: djavedt
Version: 1.0.0
Summary: Some useful datetime functions for Django
Home-page: https://github.com/dasmith2/djavedt
Author: David Smith
Author-email: dasmith2@example.com
License: UNKNOWN
Platform: UNKNOWN
Classifier: Programming Language :: Python :: 3
Classifier: License :: OSI Approved :: MIT License
Classifier: Operating System :: OS Independent
Requires-Python: >=3.6
Requires-Dist: django
